{
  "experiment": "asymmetric_focal",
  "exp_id": "df78432f",
  "config": {
    "data": {
      "dir": "/mnt/data/oss_wanjun/pai_work/open_research/dataset/ivr_sample_v16_ctcvr_sample/",
      "label_col": "ctcvr_label",
      "sample_ratio": 0.05,
      "exclude_features": [
        "deviceid"
      ]
    },
    "model": {
      "type": "mlp",
      "hidden_dims": [
        256,
        128,
        64
      ],
      "dropout": 0.3,
      "embed_dim": 16
    },
    "training": {
      "epochs": 20,
      "batch_size": 256,
      "learning_rate": 0.001,
      "patience": 5,
      "num_workers": 4
    },
    "gpu": {
      "device": -1
    },
    "loss": {
      "type": "asymmetric",
      "gamma_pos": 2.0,
      "gamma_neg": 1.0,
      "alpha": 0.25
    },
    "description": "Asymmetric Focal Loss (\u6b63\u8d1f\u6837\u672c\u4e0d\u540c gamma)"
  },
  "best_val_auc": 0.8236021135358892,
  "total_epochs": 9,
  "train_history": [
    {
      "epoch": 0,
      "loss": 0.05417963068528771
    },
    {
      "epoch": 1,
      "loss": 0.04503501503723944
    },
    {
      "epoch": 2,
      "loss": 0.043417674847520314
    },
    {
      "epoch": 3,
      "loss": 0.042186063806434256
    },
    {
      "epoch": 4,
      "loss": 0.041036244478877895
    },
    {
      "epoch": 5,
      "loss": 0.03973889617860504
    },
    {
      "epoch": 6,
      "loss": 0.03841115879348159
    },
    {
      "epoch": 7,
      "loss": 0.03710505123918341
    },
    {
      "epoch": 8,
      "loss": 0.035473964570362115
    }
  ],
  "val_history": [
    {
      "epoch": 0,
      "loss": 0.0452693084803607,
      "auc": 0.8066681444507293,
      "logloss": 0.2988417129701721,
      "pcoc": 1.168856143951416,
      "mean_pred": 0.13220155239105225,
      "mean_true": 0.11310335993766785,
      "f1": 0.0,
      "precision": 0.0,
      "recall": 0.0,
      "tp": 0,
      "fp": 0,
      "tn": 54608,
      "fn": 6964
    },
    {
      "epoch": 1,
      "loss": 0.04444510662827749,
      "auc": 0.816159027558413,
      "logloss": 0.2940174064476318,
      "pcoc": 1.1209228038787842,
      "mean_pred": 0.12678013741970062,
      "mean_true": 0.11310335993766785,
      "f1": 0.0,
      "precision": 0.0,
      "recall": 0.0,
      "tp": 0,
      "fp": 0,
      "tn": 54608,
      "fn": 6964
    },
    {
      "epoch": 2,
      "loss": 0.04399555411452574,
      "auc": 0.8228015326362206,
      "logloss": 0.2896376015125705,
      "pcoc": 1.0771886110305786,
      "mean_pred": 0.12183364480733871,
      "mean_true": 0.11310335993766785,
      "f1": 0.0,
      "precision": 0.0,
      "recall": 0.0,
      "tp": 0,
      "fp": 0,
      "tn": 54608,
      "fn": 6964
    },
    {
      "epoch": 3,
      "loss": 0.044358092456808725,
      "auc": 0.8236021135358892,
      "logloss": 0.2879002882220244,
      "pcoc": 1.1526622772216797,
      "mean_pred": 0.13036997616291046,
      "mean_true": 0.11310335993766785,
      "f1": 0.0,
      "precision": 0.0,
      "recall": 0.0,
      "tp": 0,
      "fp": 0,
      "tn": 54608,
      "fn": 6964
    },
    {
      "epoch": 4,
      "loss": 0.04430958705169779,
      "auc": 0.8223650316735029,
      "logloss": 0.2872074984704976,
      "pcoc": 1.080165147781372,
      "mean_pred": 0.12217031419277191,
      "mean_true": 0.11310335993766785,
      "f1": 0.0,
      "precision": 0.0,
      "recall": 0.0,
      "tp": 0,
      "fp": 0,
      "tn": 54608,
      "fn": 6964
    },
    {
      "epoch": 5,
      "loss": 0.04518566388806861,
      "auc": 0.8206750955438988,
      "logloss": 0.28497058717656576,
      "pcoc": 1.0561572313308716,
      "mean_pred": 0.11945493519306183,
      "mean_true": 0.11310335993766785,
      "f1": 0.0,
      "precision": 0.0,
      "recall": 0.0,
      "tp": 0,
      "fp": 0,
      "tn": 54608,
      "fn": 6964
    },
    {
      "epoch": 6,
      "loss": 0.04600260664875082,
      "auc": 0.81510034107855,
      "logloss": 0.28652648901136113,
      "pcoc": 0.9849478006362915,
      "mean_pred": 0.11140090227127075,
      "mean_true": 0.11310335993766785,
      "f1": 0.0,
      "precision": 0.0,
      "recall": 0.0,
      "tp": 0,
      "fp": 0,
      "tn": 54608,
      "fn": 6964
    },
    {
      "epoch": 7,
      "loss": 0.04754252863962868,
      "auc": 0.8146752840105399,
      "logloss": 0.2858229441961096,
      "pcoc": 0.9412128925323486,
      "mean_pred": 0.10645434260368347,
      "mean_true": 0.11310335993766785,
      "f1": 0.0,
      "precision": 0.0,
      "recall": 0.0,
      "tp": 0,
      "fp": 0,
      "tn": 54608,
      "fn": 6964
    },
    {
      "epoch": 8,
      "loss": 0.04925892143452316,
      "auc": 0.8109471276497455,
      "logloss": 0.28881255932831323,
      "pcoc": 0.98044353723526,
      "mean_pred": 0.11089146137237549,
      "mean_true": 0.11310335993766785,
      "f1": 0.0,
      "precision": 0.0,
      "recall": 0.0,
      "tp": 0,
      "fp": 0,
      "tn": 54608,
      "fn": 6964
    }
  ],
  "start_time": "2026-04-01T08:06:25.001382",
  "end_time": "2026-04-01T08:08:50.734992"
}